CHANGES.txt
CONTRIBUTORS.txt
MANIFEST.in
README.txt
setup.cfg
setup.py
collective/__init__.py
collective.ixedit.egg-info/PKG-INFO
collective.ixedit.egg-info/SOURCES.txt
collective.ixedit.egg-info/dependency_links.txt
collective.ixedit.egg-info/entry_points.txt
collective.ixedit.egg-info/namespace_packages.txt
collective.ixedit.egg-info/not-zip-safe
collective.ixedit.egg-info/paster_plugins.txt
collective.ixedit.egg-info/requires.txt
collective.ixedit.egg-info/top_level.txt
collective/ixedit/README.txt
collective/ixedit/__init__.py
collective/ixedit/config.py
collective/ixedit/configure.zcml
collective/ixedit/browser/__init__.py
collective/ixedit/browser/configure.zcml
collective/ixedit/browser/IXEdit/ixedit.css
collective/ixedit/browser/IXEdit/ixedit.packed.js
collective/ixedit/browser/IXEdit/images/bg-dark-70.png
collective/ixedit/browser/IXEdit/images/bg-dark-80.png
collective/ixedit/browser/IXEdit/images/bg-dark-heading.png
collective/ixedit/browser/IXEdit/images/bg-dark-mainbutton.png
collective/ixedit/browser/IXEdit/images/bg-dark-titlebar.png
collective/ixedit/browser/IXEdit/images/bg-light-5.png
collective/ixedit/browser/IXEdit/images/bg-light-listheader.png
collective/ixedit/browser/IXEdit/images/bg-red-50.png
collective/ixedit/browser/IXEdit/images/bg-selectorlist-y.png
collective/ixedit/browser/IXEdit/images/bg-textbox.png
collective/ixedit/browser/IXEdit/images/disclosure_triangle.png
collective/ixedit/browser/IXEdit/images/grabber-se.png
collective/ixedit/browser/IXEdit/images/ixedit-icon.png
collective/ixedit/browser/IXEdit/images/selectorarrow-y.png
collective/ixedit/browser/IXEdit/images/tiny-help.png
collective/ixedit/browser/IXEdit/images/tiny-minus-sub.png
collective/ixedit/browser/IXEdit/images/tiny-minus.png
collective/ixedit/browser/IXEdit/images/tiny-plus-sub.png
collective/ixedit/browser/IXEdit/images/tiny-plus.png
collective/ixedit/browser/IXEdit/images/tiny-route.png
collective/ixedit/browser/IXEdit/images/tiny-x.png
collective/ixedit/browser/IXEdit/images/tiny-xray.png
collective/ixedit/browser/sample-style/ui-sui.css
collective/ixedit/browser/sample-style/images/bg-button-grad.gif
collective/ixedit/browser/sample-style/images/bg-grad.gif
collective/ixedit/browser/sample-style/images/bg-header-grad.gif
collective/ixedit/browser/sample-style/images/bg-splitterh-grad.gif
