Metadata-Version: 1.0
Name: collective.ixedit
Version: 1.0
Summary: IXEdit Javascript Interaction Design Tool
Home-page: http://svn.plone.org/svn/collective/collective.ixedit
Author: Plone Foundation
Author-email: plone-developers@lists.sourceforge.net
License: GPLv3+
Keywords: ixedit plone
Platform: UNKNOWN
Classifier: Framework :: Plone
Classifier: Intended Audience :: Developers
